nafld_kbs_nav/__init__.py
nafld_kbs_nav_component-0.0.4.dist-info/METADATA
nafld_kbs_nav_component-0.0.4.dist-info/WHEEL
nafld_kbs_nav_component-0.0.4.dist-info/top_level.txt
nafld_kbs_nav_component-0.0.4.dist-info/RECORD
