Metadata-Version: 2.1
Name: nafld-kbs-nav-component
Version: 0.0.4
Summary: UNKNOWN
Home-page: 
Author: 
Author-email: 
License: UNKNOWN
Platform: UNKNOWN
Requires-Python: >=3.6
Requires-Dist: streamlit (>=0.63)
